pywappalyzer/__init__.py
pywappalyzer/exceptions.py
pywappalyzer/utils.py
pywappalyzer/wappalyzer.py
pywappalyzer/db/categories.json
pywappalyzer/db/technologies.json
tests/__init__.py
tests/conftest.py
tests/test_exceptions.py
tests/test_utils.py
tests/test_wappalyzer.py
pywappalyzer-0.1.1.dist-info/LICENSE
pywappalyzer-0.1.1.dist-info/METADATA
pywappalyzer-0.1.1.dist-info/WHEEL
pywappalyzer-0.1.1.dist-info/top_level.txt
pywappalyzer-0.1.1.dist-info/RECORD
