Metadata-Version: 2.1
Name: pywappalyzer
Version: 0.1.1
Summary: Easy identify site's technologies.json
Home-page: https://github.com/Kel0/pywappalyzer
Author: Kel0
Author-email: rozovdima123@gmail.com
License: UNKNOWN
Platform: UNKNOWN
Classifier: Programming Language :: Python :: 3
Classifier: License :: OSI Approved :: MIT License
Classifier: Operating System :: OS Independent
Requires-Python: >=3.7
Requires-Dist: geckodriver-autoinstaller
Requires-Dist: lxml
Requires-Dist: selenium
Requires-Dist: requests
Requires-Dist: requests-toolbelt
Requires-Dist: beautifulsoup4
